[{"hora": 0, "vel_movil": 30.4, "vel_media": 25.8}, {"hora": 1, "vel_movil": 27.4, "vel_media": 11.4}, {"hora": 2, "vel_movil": 26.6, "vel_media": 10.2}, {"hora": 3, "vel_movil": 30.1, "vel_media": 7.6}, {"hora": 4, "vel_movil": 33.7, "vel_media": 18.4}, {"hora": 5, "vel_movil": 26.0, "vel_media": 18.4}, {"hora": 6, "vel_movil": 27.5, "vel_media": 21.8}, {"hora": 7, "vel_movil": 26.3, "vel_media": 20.4}, {"hora": 8, "vel_movil": 27.2, "vel_media": 21.8}, {"hora": 9, "vel_movil": 28.0, "vel_media": 22.9}, {"hora": 10, "vel_movil": 27.6, "vel_media": 22.4}, {"hora": 11, "vel_movil": 27.2, "vel_media": 21.9}, {"hora": 12, "vel_movil": 26.9, "vel_media": 21.3}, {"hora": 13, "vel_movil": 26.7, "vel_media": 21.1}, {"hora": 14, "vel_movil": 26.9, "vel_media": 21.4}, {"hora": 15, "vel_movil": 26.7, "vel_media": 21.1}, {"hora": 16, "vel_movil": 26.4, "vel_media": 20.8}, {"hora": 17, "vel_movil": 25.8, "vel_media": 19.9}, {"hora": 18, "vel_movil": 25.4, "vel_media": 19.5}, {"hora": 19, "vel_movil": 26.3, "vel_media": 20.7}, {"hora": 20, "vel_movil": 27.3, "vel_media": 21.9}, {"hora": 21, "vel_movil": 28.3, "vel_media": 23.2}, {"hora": 22, "vel_movil": 30.1, "vel_media": 25.4}, {"hora": 23, "vel_movil": 32.1, "vel_media": 28.2}]